{
    "title": "Cyborg 009",
    "alternative_title": "\u30b5\u30a4\u30dc\u30fc\u30b0009",
    "slug": "cyborg-009",
    "anime_type": "TV Series",
    "description": "The evil Black Ghost organization kidnapped several people from around the world and turned them into cyborgs designed to be perfect weapons, but their evil plan backfires because the nine cyborgs still retain some of their humanity. Once the cyborgs escape, they vow to defeat the Black Ghost and bring peace to mankind.",
    "genre": "[<Genre -> Action>, <Genre -> Adventure>, <Genre -> Mecha>, <Genre -> Sci-Fi>, <Genre -> Shounen>]",
    "year": "1968",
    "status": "Completed",
    "total_episodes": "51"
}