{
    "title": "Dash! Yonkurou",
    "alternative_title": "\u30c0\u30c3\u30b7\u30e5\uff01\u56db\u99c6\u90ce",
    "slug": "dash-yonkurou",
    "anime_type": "TV Series",
    "description": "The story is a succession of races in imaginative paths and runs to suit her run. The story will focus increasingly what is the real Emperor, will be discovered having this many mini title that will compare against the Emperor of Yonkuro, the epilogue to the epic challenge of the Rally of hell in this race will challenge a group of thugs who want to take advantage of Best of Mini 4WD racers to be able to recover a hidden treasure.The story centers on a brother and sister, Tatsuya and Kiyoko, the children of a scientist at the Twin X facility. This story is used by the very popular main character Yonkuro Hinomaru.",
    "genre": "[<Genre -> Action>, <Genre -> Cars>, <Genre -> Kids>, <Genre -> Shounen>, <Genre -> Sports>]",
    "year": "1989",
    "status": "Completed",
    "total_episodes": "25"
}