{
    "title": "Diamond Daydreams",
    "alternative_title": "Kita e.: Diamond Dust Drops, \u5317\u3078\u3002 \uff5eDiamond Dust Drops\uff5e",
    "slug": "diamond-daydreams",
    "anime_type": "TV Series",
    "description": "If a couple sees the diamond dust together, then they will certainly find eternal happiness. Or so it is said. This is a drama about the romances, friendships and conflicts of six girls from Hokkaido and how the diamond dust affects them and eventually links them together in the search for happiness.",
    "genre": "[<Genre -> Drama>, <Genre -> Romance>, <Genre -> Slice of Life>]",
    "year": "2004",
    "status": "Completed",
    "total_episodes": "13"
}