{
    "title": "Godannar",
    "alternative_title": "Shinkon Gattai Godannar!!, Marriage of God & Soul Godannar!!, \u795e\u9b42\u5408\u4f53\u30b4\u30fc\u30c0\u30f3\u30ca\u30fc\uff01\uff01",
    "slug": "godannar",
    "anime_type": "TV Series",
    "description": "Her father passed away very early and her mother lives and works in a crowded Chinese restaurant. Kitajima Maya, a 13-year old girl, has to carry the burden of making ends meet as she fights against her ill fate. However, she is able to overcome the trials and tribulations in her life with her passion and enthusiasm. She happens to encounter the reclusive actress Tsukikage who decides to train and mould her into the foremost actress of her generation.",
    "genre": "[<Genre -> Comedy>, <Genre -> Ecchi>, <Genre -> Mecha>, <Genre -> Romance>, <Genre -> Sci-Fi>]",
    "year": "2003",
    "status": "Completed",
    "total_episodes": "26"
}