{
    "title": "Jigoku Shoujo Futakomori",
    "alternative_title": "Hell Girl: Two Mirrors, \u5730\u7344\u5c11\u5973 \u4e8c\u7c60",
    "slug": "jigoku-shoujo-futakomori",
    "anime_type": "TV Series",
    "description": "Enma Ai once again returns as the Jigoku Shoujo, who uses Jigoku Tsuushin (Hell Hotline) to allow people to post their grudges on their tormentors, sending them straight to Hell. In exchange, the users of the website will end up in Hell after they die. Meanwhile, a mysterious girl with blue eyes called Kikuri appears and seems to have strange intentions towards Ai and Jigoku Tsuushin's operation.",
    "genre": "[<Genre -> Horror>, <Genre -> Psychological>, <Genre -> Supernatural>]",
    "year": "2006",
    "status": "Completed",
    "total_episodes": "26"
}