{
    "title": "Jin-Roh The Wolf Brigade",
    "alternative_title": "\u4eba\u72fc JIN-ROH",
    "slug": "jin-roh-the-wolf-brigade",
    "anime_type": "Movie",
    "description": "In the riot-torn 1960's Tokyo of an alternate history... a special police force, the\u00a0Capitol Police Organization\u00a0(CAPO) has been formed. Within CAPO is the special unit that gets the toughest jobs. Some of the men in the unit, according to rumour, comprise a vigilante group called the\u00a0Wolf Brigade.\u00a0Fuse, a member of the special unit, broods obsessively about a terrorist girl who blew herself up in front of him. Then he meets the girl's sister and becomes emotionally involved...",
    "genre": "[<Genre -> Drama>, <Genre -> Military>, <Genre -> Police>, <Genre -> Psychological>, <Genre -> Romance>]",
    "year": "1998",
    "status": "Completed",
    "total_episodes": "1"
}