{
    "title": "Kiddy Grade: Truth Dawn",
    "alternative_title": "\u30ad\u30c7\u30a3\u30fb\u30b0\u30ec\u30a4\u30c9\u3000\u5287\u5834\u7248\u3000\u7b2c\u4e09\u90e8: \u9ece\u660e\u7bc7",
    "slug": "kiddy-grade-truth-dawn",
    "anime_type": "Movie",
    "description": "This Movie is the retelling of the original anime's final.",
    "genre": "[<Genre -> Action>, <Genre -> Mecha>, <Genre -> Sci-Fi>, <Genre -> Super Power>]",
    "year": "2007",
    "status": "Completed",
    "total_episodes": "1"
}