{
    "title": "Magia Record: Mahou Shoujo Madoka\u2606Magica Gaiden (TV) 2nd Season",
    "alternative_title": "\u30de\u30ae\u30a2\u30ec\u30b3\u30fc\u30c9 \u9b54\u6cd5\u5c11\u5973\u307e\u3069\u304b\u2606\u30de\u30ae\u30ab\u5916\u4f1d 2nd Season",
    "slug": "magia-record-mahou-shoujo-madokamagica-gaiden-tv-2nd-season",
    "anime_type": "TV Series",
    "description": "2nd Season of Magia Record: Mahou Shoujo Madoka\u2606Magica Gaiden (TV).",
    "genre": "[<Genre -> Drama>, <Genre -> Magic>, <Genre -> Psychological>, <Genre -> Thriller>]",
    "year": "6969",
    "status": "Upcoming",
    "total_episodes": "0"
}