{
    "title": "MekakuCity Actors",
    "alternative_title": "\u30e1\u30ab\u30af\u30b7\u30c6\u30a3\u30a2\u30af\u30bf\u30fc\u30ba",
    "slug": "mekaku-city-actors",
    "anime_type": "Spring 2014 Anime",
    "description": "Shintaro Kisaragi, a HikiNEET who shut himself inside his room for 2 years, had been living his life normally until he met a cyber girl named Ene, who appeared in his computer screen when someone anonymously sent him a mysterious e-mail one year ago. One day, Ene messes with Shintaro's PC which causes him to go outside for the first time in two years.",
    "genre": "[<Genre -> Comedy>, <Genre -> Romance>, <Genre -> Sci-Fi>, <Genre -> Supernatural>]",
    "year": "2014",
    "status": "Completed",
    "total_episodes": "12"
}