{
    "title": "Onegai Teacher",
    "alternative_title": "Please Teacher!, \u304a\u306d\u304c\u3044\u2606\u30c6\u30a3\u30fc\u30c1\u30e3\u30fc",
    "slug": "onegai-teacher",
    "anime_type": "TV Series",
    "description": "Kusanagi Kei, a high-school student living with his aunt and uncle, has an encounter with a female alien. This alien is revealed to be a new teacher at his school. Later, he is forced to marry this alien to preserve her secrets. From there, various romantically-inclined problems crop up repeatedly.",
    "genre": "[<Genre -> Romance>, <Genre -> Sci-Fi>]",
    "year": "2002",
    "status": "Completed",
    "total_episodes": "13"
}