{
    "title": "Ore Monogatari!!",
    "alternative_title": "My Love Story!!, \u4ffa\u7269\u8a9e!!",
    "slug": "ore-monogatari-",
    "anime_type": "Spring 2015 Anime",
    "description": "Gouda Takeo is a freshman in high school. (Both estimates) Weight: 120kg, Height: 2 meters. He spends his days peacefully with his super-popular-with-girls, yet insensitive childhood friend, Sunakawa. One morning, on the train to school, Takeo saves a girl, Yamato, from being molested by a pervert. Could this be the beginning of spring for Takeo?",
    "genre": "[<Genre -> Comedy>, <Genre -> Romance>, <Genre -> Shoujo>]",
    "year": "2015",
    "status": "Completed",
    "total_episodes": "24"
}