{
    "title": "Project ARMS",
    "alternative_title": "ARMS, \u30d7\u30ed\u30b8\u30a7\u30af\u30c8\u30a2\u30fc\u30e0\u30ba",
    "slug": "project-arms",
    "anime_type": "TV Series",
    "description": "When in kindergarten a boy gets involved in an accident that is horrible damaging his arm. Somehow the doctors manage to save it. Now, several years later, his arm seems to become the focus of strange events, as it turns out that it's more than just a normal arm. Because of that a secret organization is out to get hold of him and the power he possesses.",
    "genre": "[<Genre -> Action>, <Genre -> Martial Arts>, <Genre -> Super Power>]",
    "year": "2001",
    "status": "Completed",
    "total_episodes": "52"
}