{
    "title": "Sakura Taisen: Gouka Kenran",
    "alternative_title": "Sakura Wars: The Gorgeous Blooming Cherry Blossoms, Sakura Wars OVA 2,   \u30b5\u30af\u30e9\u5927\u6226 \u8f5f\u83ef\u7d62\u721b",
    "slug": "sakura-taisen-gouka-kenran",
    "anime_type": "OVA",
    "description": "The end of the demon wars has ended and now the Flower Division has been able to rest up after their fighting. The second Sakura Wars developes studies on every Flower Division Combatee in every episode while they go on their miscellanious adventures around Japan.",
    "genre": "[<Genre -> Adventure>, <Genre -> Mecha>, <Genre -> Sci-Fi>, <Genre -> Shounen>]",
    "year": "1999",
    "status": "Completed",
    "total_episodes": "6"
}