{
    "title": "Shippuu! Iron Leaguer",
    "alternative_title": "Hurricane! Iron Leaguer, \u75be\u98a8\uff01 \u30a2\u30a4\u30a2\u30f3\u30ea\u30fc\u30ac\u30fc",
    "slug": "shippuu-iron-leaguer",
    "anime_type": "TV Series",
    "description": "The Iron League: a place where teams of robots, under individual \"owners\", play various sports and duke it out in tournaments. Mach Windy is a member of Dark Prince, a team that doesn't play fair and fights dirty to win. Unsatisfied with the actions of his teammates, he defects against the will of Dark Prince's nefarious owner and joins Silver Prince: the weakest team in the league. Alongside faithful companions such as Magnum Ace and Bull Armor, Mach Windy and Silver Prince will battle against Dark Prince in games of soccer and baseball, and aim for the top!",
    "genre": "[<Genre -> Mecha>, <Genre -> Sci-Fi>, <Genre -> Shounen>, <Genre -> Sports>]",
    "year": "1993",
    "status": "Completed",
    "total_episodes": "52"
}