{
    "title": "Starmyu 2nd Season",
    "alternative_title": "Koukou Hoshi Kageki 2nd Season, High School Star Musical 2nd Season, Starmu, \u9ad8\u6821\u661f\u6b4c\u5287\uff3b\u30b9\u30bf\u30df\u30e5\uff3d",
    "slug": "starmyu-2nd-season",
    "anime_type": "Spring 2017 Anime",
    "description": "Second season of the Starmyu television series.",
    "genre": "[<Genre -> Music>, <Genre -> School>, <Genre -> Slice of Life>]",
    "year": "2017",
    "status": "Completed",
    "total_episodes": "12"
}