{
    "title": "Stitch!: Zutto Saikou no Tomodachi (Dub)",
    "alternative_title": "Stitch! 3",
    "slug": "stitch-zutto-saikou-no-tomodachi-dub",
    "anime_type": "TV Series",
    "description": "In their new adventure, Yuuna and Stitch move from their small island Izayoi to the Okinawa main island where Yuuna is supposed to visit a school. A new cast of friends awaits them there as well as a new crisis approaching from space.",
    "genre": "[<Genre -> Adventure>, <Genre -> Comedy>, <Genre -> Kids>]",
    "year": "2010",
    "status": "Completed",
    "total_episodes": "30"
}