{
    "title": "Tales From Earthsea",
    "alternative_title": "Gedo Senki, \u30b2\u30c9\u6226\u8a18",
    "slug": "tales-from-earthsea",
    "anime_type": "Movie",
    "description": "It tells the story of\u00a0Ged, the most powerful wizard in Earthsea, and his attempts to protect\u00a0Prince Arren\u00a0from the evil machinations of rival wizard Cob. Together with\u00a0Therru, a young girl he rescues from slave takers, Arren must unite with Ged to defeat Cob and return balance to their world.",
    "genre": "[<Genre -> Adventure>, <Genre -> Fantasy>, <Genre -> Magic>]",
    "year": "2006",
    "status": "Completed",
    "total_episodes": "1"
}