{
    "title": "Tekken: Blood Vengeance",
    "alternative_title": "\u9244\u62f3 BLOOD VENGEANCE",
    "slug": "tekken-blood-vengeance",
    "anime_type": "Movie",
    "description": "High school student\u00a0Ling Xiaoyu\u00a0is recruited by\u00a0Anna Williams\u00a0of\u00a0G Corporation\u00a0to transfer to Kyoto University and gather information on a student named\u00a0Kamiya Shin. Meanwhile,\u00a0Kazama Jin, the current head of theMishima Zaibatsu, sends\u00a0Alisa Bosconovitch\u00a0to the university for the same mission. Though they do not know each other's true motives, Xiaoyu and Alisa become close friends. However, their friendship is put to the test when Shin is captured by an unknown assailant.",
    "genre": "[<Genre -> Action>, <Genre -> Fantasy>, <Genre -> Martial Arts>, <Genre -> Sci-Fi>, <Genre -> Supernatural>]",
    "year": "2011",
    "status": "Completed",
    "total_episodes": "1"
}